AuraAlerts/AuraAlerts.py
AuraAlerts/__init__.py
AuraAlerts/ScreenShots/CUSTOM.png
AuraAlerts/ScreenShots/ERROR.png
AuraAlerts/ScreenShots/INFO.png
AuraAlerts/ScreenShots/SUCCESS.png
AuraAlerts/ScreenShots/WARN.png
AuraAlerts/imgs/check.png
AuraAlerts/imgs/close.png
AuraAlerts/imgs/custom.png
AuraAlerts/imgs/icon.png
AuraAlerts/imgs/info.png
AuraAlerts/imgs/warn.png
AuraAlerts-1.0.dist-info/LICENSE.txt
AuraAlerts-1.0.dist-info/METADATA
AuraAlerts-1.0.dist-info/WHEEL
AuraAlerts-1.0.dist-info/top_level.txt
AuraAlerts-1.0.dist-info/RECORD
