Metadata-Version: 2.1
Name: AuraAlerts
Version: 1.0
Summary: Simple Alerts For Desktop App Developers!!
Home-page: https://github.com/abdrzakk/AuraAlerts/
Author: abdrzakk
Keywords: AuraAlerts,Alerts,messagebox,alerts,aura
Classifier: Operating System :: OS Independent
Classifier: Programming Language :: Python :: 3
Classifier: License :: OSI Approved :: MIT License
Requires: customtkinter
Requires: Pillow
Requires: os
License-File: LICENSE.txt
